profiler/Comparer.py
profiler/__init__.py
profiler/monitor.py
profiler/profiler.py
CodeProfiler-1.0.0.1.7.dist-info/LICENSE.txt
CodeProfiler-1.0.0.1.7.dist-info/METADATA
CodeProfiler-1.0.0.1.7.dist-info/WHEEL
CodeProfiler-1.0.0.1.7.dist-info/top_level.txt
CodeProfiler-1.0.0.1.7.dist-info/RECORD
