Metadata-Version: 2.1
Name: CodeProfiler
Version: 1.0.0.1.7
Summary: Print memory and cpu usage
Home-page: https://github.com/connosieurofdoom/profiler
Author: Shreyas
Author-email: shreyasajitrajendran@gmail.com
License: UNKNOWN
Platform: UNKNOWN
Classifier: Programming Language :: Python :: 3
Classifier: Development Status :: 1 - Planning
Classifier: License :: OSI Approved :: GNU General Public License (GPL)
Classifier: Operating System :: OS Independent
Requires-Python: >=3.6
